{
  "tags": [
    {
      "serial": 123,
      "name": "Harith mar",


      "userType": "Drir",


      "status": "Actve"
    },

    {
      "serial": 123,
      "name": "Harith Kumar",
      "userType": "Maintenance",
      "status": "Active"
    },
    {
      "serial": 123,

      "name": "Harith Kumar",

      "userType": "Driver",

      "status": "Acdgktrikhive"
    },

    {
      "serial": 123,
      "name": "Hariqkrkmgmgth Kumar",
      "userType": "Driver",
      "status": "Active"
    },

    {
      "serial": 123,
      "name": "Harith Kumar",
      "userType": "Driver",
      "status": "Active"
    },

    {
      "serial": 123,
      "name": "Haramkmfith Kumar",
      "userType": "Driver",
      "status": "Acarrtive"
    },


    {
      "serial": 123,
      "name": "Harith Kumar",
      "userType": "Driver",
      "status": "Active"
    },

    {
      "serial": 123,
      "name": "Harith Kumar",
      "userType": "Driver",
      "status": "Active",
    },

    {
      "serial": 123,
      "name": "Harith Kumar",
      "userType": "Driver",
      "status": "Active",
    },

    {
      "serial": 123,
      "name": "Harith Kumar",
      "userType": "Driver",
      "status": "Active"
    },



    {
      "serial": 123,
      "name": "Harith Kumar",
      "userType": "Driver",
      "status": "Actammfkive"
    },

    {
      "serial": 123,
      "name": "Harithamkkmr Kumar",
      "userType": "Driver",
      "status": "Active"
    },



    {
      "serial": 123,
      "name": "Harith Kumar",
      "userType": "Driver",
      "status": "Active"
    }
  ]
}


